openbim/__main__.py
openbim/peri.py
openbim/csi/__init__.py
openbim/csi/__main__.py
openbim/csi/bridge.py
openbim/csi/config.py
openbim/csi/frame.py
openbim/csi/link.py
openbim/csi/parse.py
openbim/csi/pattern.py
openbim/csi/point.py
openbim/csi/schema.py
openbim/csi/tables.py
openbim/csi/utility.py
openbim/csi/api/etabs_utilities.py
openbim/csi/api/general_utilities.py
openbim/csi/api/main.py
openbim/csi/api/opensees_postprocessor.py
openbim/csi/api/opensees_utilities.py
openbim/ifc/__main__.py
openbim/ifc/analysis.py
openbim/ifc/export.py
openbim/ifc/meshing.py
openbim/inp/__init__.py
openbim/inp/__main__.py
openbim/inp/model.py
openbim/inp/parser.py
openbim/msh/__init__.py
openbim/msh/element.py
openbim/msh/nodes.py
openbim/msh/utils.py
openbim/msh/viz.py
openbim/msh/examples/example1.py
openbim/msh/examples/example2.py
openbim/msh/examples/example3.py
openbim/msh/examples/example4.py
openbim/msh/examples/example5.py
simm-0.0.0.dist-info/LICENSE
simm-0.0.0.dist-info/METADATA
simm-0.0.0.dist-info/WHEEL
simm-0.0.0.dist-info/entry_points.txt
simm-0.0.0.dist-info/top_level.txt
simm-0.0.0.dist-info/RECORD
